<annotation>
	<folder>5deb576d1dc17d7c5515ad0b</folder>
	<filename>5deb576d1dc17d7c5515ad0b_1594975280.jpg</filename>
	<path>/Users/akahuy12/Downloads/5deb576d1dc17d7c5515ad0b/5deb576d1dc17d7c5515ad0b_1594975280.jpg</path>
	<source>
		<database>Unknown</database>
	</source>
	<size>
		<width>506</width>
		<height>286</height>
		<depth>3</depth>
	</size>
	<segmented>0</segmented>
	<object>
		<name>xe_hoi</name>
		<pose>Unspecified</pose>
		<truncated>0</truncated>
		<difficult>0</difficult>
		<bndbox>
			<xmin>117</xmin>
			<ymin>80</ymin>
			<xmax>200</xmax>
			<ymax>114</ymax>
		</bndbox>
	</object>
	<object>
		<name>xe_buyt</name>
		<pose>Unspecified</pose>
		<truncated>0</truncated>
		<difficult>0</difficult>
		<bndbox>
			<xmin>22</xmin>
			<ymin>50</ymin>
			<xmax>66</xmax>
			<ymax>100</ymax>
		</bndbox>
	</object>
	<object>
		<name>xe_may</name>
		<pose>Unspecified</pose>
		<truncated>0</truncated>
		<difficult>0</difficult>
		<bndbox>
			<xmin>169</xmin>
			<ymin>116</ymin>
			<xmax>207</xmax>
			<ymax>158</ymax>
		</bndbox>
	</object>
	<object>
		<name>xe_may</name>
		<pose>Unspecified</pose>
		<truncated>0</truncated>
		<difficult>0</difficult>
		<bndbox>
			<xmin>184</xmin>
			<ymin>156</ymin>
			<xmax>230</xmax>
			<ymax>211</ymax>
		</bndbox>
	</object>
	<object>
		<name>xe_may</name>
		<pose>Unspecified</pose>
		<truncated>0</truncated>
		<difficult>0</difficult>
		<bndbox>
			<xmin>161</xmin>
			<ymin>190</ymin>
			<xmax>209</xmax>
			<ymax>249</ymax>
		</bndbox>
	</object>
	<object>
		<name>xe_may</name>
		<pose>Unspecified</pose>
		<truncated>0</truncated>
		<difficult>0</difficult>
		<bndbox>
			<xmin>98</xmin>
			<ymin>146</ymin>
			<xmax>128</xmax>
			<ymax>201</ymax>
		</bndbox>
	</object>
	<object>
		<name>xe_may</name>
		<pose>Unspecified</pose>
		<truncated>0</truncated>
		<difficult>0</difficult>
		<bndbox>
			<xmin>115</xmin>
			<ymin>115</ymin>
			<xmax>146</xmax>
			<ymax>158</ymax>
		</bndbox>
	</object>
	<object>
		<name>xe_may</name>
		<pose>Unspecified</pose>
		<truncated>0</truncated>
		<difficult>0</difficult>
		<bndbox>
			<xmin>26</xmin>
			<ymin>99</ymin>
			<xmax>56</xmax>
			<ymax>134</ymax>
		</bndbox>
	</object>
	<object>
		<name>xe_may</name>
		<pose>Unspecified</pose>
		<truncated>0</truncated>
		<difficult>0</difficult>
		<bndbox>
			<xmin>118</xmin>
			<ymin>34</ymin>
			<xmax>140</xmax>
			<ymax>54</ymax>
		</bndbox>
	</object>
</annotation>
